skylark_lcp/__init__.py
skylark_lcp/main.py
skylark_lcp-0.0.1.dist-info/METADATA
skylark_lcp-0.0.1.dist-info/WHEEL
skylark_lcp-0.0.1.dist-info/top_level.txt
skylark_lcp-0.0.1.dist-info/RECORD
