Metadata-Version: 2.1
Name: skylark_lcp
Version: 0.0.1
Summary: This is the official package of the LCP project.
Author: Skylark Labs
Requires-Dist: transformers >=4.41.0
Requires-Dist: numpy >=1.17
Requires-Dist: huggingface-hub >=0.23.0
Requires-Dist: safetensors >=0.4.1
Requires-Dist: charset-normalizer <4,>=2
Requires-Dist: certifi >=2017.4.17
Requires-Dist: idna <4,>=2.5
Requires-Dist: urllib3 <3,>=1.21.1
Requires-Dist: fsspec >=2023.5.0
Requires-Dist: typing-extensions >=3.7.4.3
Requires-Dist: packaging >=20.0
Requires-Dist: tqdm >=4.27
Requires-Dist: tokenizers <0.20,>=0.19
Requires-Dist: requests >2.32.2
Requires-Dist: pyyaml >=5.1
Requires-Dist: regex !=2019.12.17
Requires-Dist: gliner >=0.2.0
Requires-Dist: torch >=2.3.1
Requires-Dist: opencv-python >=4.9.0.80
Requires-Dist: regex >=2024.5.15
Requires-Dist: pandas >=1.3.5
Requires-Dist: datasets >=2.19.1
Requires-Dist: pillow >=10.3.0
Requires-Dist: librosa >=0.10.2.post1
Requires-Dist: langdetect >=1.0.9
Requires-Dist: moviepy >=1.0.3
Requires-Dist: wheel >=0.43.0
